LICENSE.txt
setup.py
calou.egg-info/PKG-INFO
calou.egg-info/SOURCES.txt
calou.egg-info/dependency_links.txt
calou.egg-info/top_level.txt
code/__init__.py