Metadata-Version: 2.1
Name: calou
Version: 0.1
Summary: SimpleCal
Author: Rakwan
Classifier: Programming Language :: Python :: 3
Classifier: License :: OSI Approved :: MIT License
Classifier: Operating System :: OS Independent
License-File: LICENSE.txt
